fancifypy/__init__.py
fancifypy/__main__.py
fancifypy/cli.py
fancifypy/fancifier.py
fancifypy-0.1.0.dist-info/METADATA
fancifypy-0.1.0.dist-info/WHEEL
fancifypy-0.1.0.dist-info/entry_points.txt
fancifypy-0.1.0.dist-info/top_level.txt
fancifypy-0.1.0.dist-info/RECORD
