Metadata-Version: 2.4
Name: fancifypy
Version: 0.1.0
Summary: Code formatter to get less boring Python files
Author-email: Yngve Mardal Moe <yngve.m.moe@gmail.com>
License: MIT
Requires-Python: >=3.10
Requires-Dist: typer
